uplink/__about__.py
uplink/__init__.py
uplink/_extras.py
uplink/arguments.py
uplink/auth.py
uplink/builder.py
uplink/commands.py
uplink/compat.py
uplink/decorators.py
uplink/exceptions.py
uplink/helpers.py
uplink/hooks.py
uplink/interfaces.py
uplink/models.py
uplink/ratelimit.py
uplink/returns.py
uplink/session.py
uplink/types.py
uplink/utils.py
uplink/clients/__init__.py
uplink/clients/aiohttp_.py
uplink/clients/exceptions.py
uplink/clients/interfaces.py
uplink/clients/register.py
uplink/clients/requests_.py
uplink/clients/twisted_.py
uplink/clients/io/__init__.py
uplink/clients/io/asyncio_strategy.py
uplink/clients/io/blocking_strategy.py
uplink/clients/io/execution.py
uplink/clients/io/interfaces.py
uplink/clients/io/state.py
uplink/clients/io/templates.py
uplink/clients/io/transitions.py
uplink/clients/io/twisted_strategy.py
uplink/converters/__init__.py
uplink/converters/interfaces.py
uplink/converters/keys.py
uplink/converters/marshmallow_.py
uplink/converters/register.py
uplink/converters/standard.py
uplink/converters/typing_.py
uplink/retry/__init__.py
uplink/retry/_helpers.py
uplink/retry/backoff.py
uplink/retry/retry.py
uplink/retry/stop.py
uplink/retry/when.py
cognifloyd_uplink-0.10.0.dist-info/AUTHORS.rst
cognifloyd_uplink-0.10.0.dist-info/LICENSE
cognifloyd_uplink-0.10.0.dist-info/METADATA
cognifloyd_uplink-0.10.0.dist-info/WHEEL
cognifloyd_uplink-0.10.0.dist-info/top_level.txt
cognifloyd_uplink-0.10.0.dist-info/RECORD
