Metadata-Version: 2.1
Name: cognifloyd-uplink
Version: 0.10.0
Summary: A Declarative HTTP Client for Python.
Home-page: https://uplink.readthedocs.io/
Author: P. Raj Kumar
Author-email: raj.pritvi.kumar@gmail.com
License: MIT
Keywords: http api rest client retrofit
Platform: UNKNOWN
Classifier: Development Status :: 4 - Beta
Classifier: Intended Audience :: Developers
Classifier: License :: OSI Approved :: MIT License
Classifier: Programming Language :: Python :: 2
Classifier: Programming Language :: Python :: 2.7
Classifier: Programming Language :: Python :: 3
Classifier: Programming Language :: Python :: 3.3
Classifier: Programming Language :: Python :: 3.4
Classifier: Programming Language :: Python :: 3.5
Classifier: Programming Language :: Python :: 3.6
Classifier: Programming Language :: Python :: 3.7
Classifier: Programming Language :: Python :: Implementation :: CPython
Classifier: Programming Language :: Python :: Implementation :: PyPy
Requires-Dist: requests (>=2.18.0)
Requires-Dist: six (>=1.12.0)
Requires-Dist: uritemplate (>=3.0.0)
Provides-Extra: aiohttp
Requires-Dist: aiohttp (>=2.3.0) ; (python_version >= '3.4') and extra == 'aiohttp'
Provides-Extra: marshmallow
Requires-Dist: marshmallow (>=2.15.0) ; extra == 'marshmallow'
Provides-Extra: tests
Requires-Dist: pytest (==4.6.5) ; extra == 'tests'
Requires-Dist: pytest-mock ; extra == 'tests'
Requires-Dist: pytest-cov ; extra == 'tests'
Requires-Dist: pytest-twisted ; extra == 'tests'
Provides-Extra: twisted
Requires-Dist: twisted (>=17.1.0) ; (python_version != '3.3' and python_version != '3.4') and extra == 'twisted'
Requires-Dist: twisted (<=17.9.0) ; (python_version == '3.3') and extra == 'twisted'
Requires-Dist: twisted (<=19.2.1) ; (python_version == '3.4') and extra == 'twisted'
Provides-Extra: typing
Requires-Dist: typing (>=3.6.4) ; extra == 'typing'
